{"web":{"client_id":"1089986280765-t1f2vk440retg7d4o747bv31egb1vcqc.apps.googleusercontent.com","project_id":"kingdom-studios-0kzeje","auth_uri":"https://accounts.google.com/o/oauth2/auth","token_uri":"https://oauth2.googleapis.com/token","auth_provider_x509_cert_url":"https://www.googleapis.com/oauth2/v1/certs","client_secret":"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","redirect_uris":["http://localhost:19006/auth/google/callback","http://localhost:3000/auth/google/callback","http://127.0.0.1:19006/auth/google/callback","http://localhost:8081/auth/google/callback","https://auth.expo.io/@dtritz9/kingdom-studios"]}}