{
  "state": "MN",
  "generatedAt": "2025-09-19T21:57:24.090Z",
  "counties": [
    {
      "county": "Anoka",
      "totalLawyers": 1,
      "verifiedLawyers": 1,
      "activeLawyers": 1,
      "unverifiedLawyers": 0,
      "lastVerified": null,
      "lawyers": [
        {
          "name": "Karen Johnson 4, Esq.",
          "verified": true,
          "active": true,
          "status": "Unknown",
          "license": "Unknown",
          "verifiedAt": "2025-09-19T21:50:25.647Z"
        }
      ],
      "verificationRate": 100
    },
    {
      "county": "Dakota",
      "totalLawyers": 1,
      "verifiedLawyers": 1,
      "activeLawyers": 1,
      "unverifiedLawyers": 0,
      "lastVerified": null,
      "lawyers": [
        {
          "name": "Karen Johnson 3, Esq.",
          "verified": true,
          "active": true,
          "status": "Unknown",
          "license": "Unknown",
          "verifiedAt": "2025-09-19T21:50:25.647Z"
        }
      ],
      "verificationRate": 100
    },
    {
      "county": "Hennepin",
      "totalLawyers": 1,
      "verifiedLawyers": 1,
      "activeLawyers": 1,
      "unverifiedLawyers": 0,
      "lastVerified": null,
      "lawyers": [
        {
          "name": "Karen Johnson, Esq.",
          "verified": true,
          "active": true,
          "status": "Unknown",
          "license": "Unknown",
          "verifiedAt": "2025-09-19T21:50:25.647Z"
        }
      ],
      "verificationRate": 100
    },
    {
      "county": "Ramsey",
      "totalLawyers": 1,
      "verifiedLawyers": 1,
      "activeLawyers": 1,
      "unverifiedLawyers": 0,
      "lastVerified": null,
      "lawyers": [
        {
          "name": "Karen Johnson 2, Esq.",
          "verified": true,
          "active": true,
          "status": "Unknown",
          "license": "Unknown",
          "verifiedAt": "2025-09-19T21:50:25.647Z"
        }
      ],
      "verificationRate": 100
    },
    {
      "county": "Washington",
      "totalLawyers": 1,
      "verifiedLawyers": 1,
      "activeLawyers": 1,
      "unverifiedLawyers": 0,
      "lastVerified": null,
      "lawyers": [
        {
          "name": "Karen Johnson 5, Esq.",
          "verified": true,
          "active": true,
          "status": "Unknown",
          "license": "Unknown",
          "verifiedAt": "2025-09-19T21:50:25.647Z"
        }
      ],
      "verificationRate": 100
    }
  ],
  "summary": {
    "totalLawyers": 5,
    "verifiedLawyers": 5,
    "activeLawyers": 5,
    "unverifiedLawyers": 0,
    "verificationRate": 100
  }
}